{"_type":"export","__export_format":4,"__export_date":"2022-03-04T14:53:43.667Z","__export_source":"insomnia.desktop.app:v2021.7.2","resources":[{"_id":"req_3c0066cff8464cdabcfdcbe0e3e363ed","parentId":"fld_bf988367be0f4889be7cfdcf2d76706d","modified":1646405238170,"created":1646404208685,"url":"http://localhost/ballroom/index.php/provider/loginFornecedor","name":"Login Fornecedor","description":"","method":"POST","body":{"mimeType":"application/x-www-form-urlencoded","params":[{"id":"pair_25d236ea286e401f93dc8284b5cf04fc","name":"email","value":"wagner1107@gmail.com","description":""},{"id":"pair_6b4a548635e241fba4a449773bb02a44","name":"password","value":"123456","description":""}]},"parameters":[],"headers":[{"id":"pair_a459fc0119df40159d3c27fc59e2f91d","name":"","value":"","description":""},{"name":"Content-Type","value":"application/x-www-form-urlencoded","id":"pair_6af7f290a4d04a1aad439af3e7af99b6"}],"authentication":{},"metaSortKey":-1645396281651.5,"isPrivate":false,"settingStoreCookies":true,"settingSendCookies":true,"settingDisableRenderRequestBody":false,"settingEncodeUrl":true,"settingRebuildPath":true,"settingFollowRedirects":"global","_type":"request"},{"_id":"fld_bf988367be0f4889be7cfdcf2d76706d","parentId":"fld_630a70b7f84843d496869868e8ad5ab9","modified":1646359843737,"created":1646359843737,"name":"Fornecedor","description":"","environment":{},"environmentPropertyOrder":null,"metaSortKey":-1646359843737,"_type":"request_group"},{"_id":"fld_630a70b7f84843d496869868e8ad5ab9","parentId":"wrk_cf0f3856a17c4040b96c56899e3e63b0","modified":1646359014084,"created":1646359014084,"name":"BallRoom","description":"","environment":{},"environmentPropertyOrder":null,"metaSortKey":-1646359014084,"_type":"request_group"},{"_id":"wrk_cf0f3856a17c4040b96c56899e3e63b0","parentId":null,"modified":1646405606051,"created":1643397915286,"name":"Teste Wagner Augusto","description":"","scope":"collection","_type":"workspace"},{"_id":"req_fea8b53f8e57445f9998f94a24aa529e","parentId":"fld_bf988367be0f4889be7cfdcf2d76706d","modified":1646402845496,"created":1646359060311,"url":"http://localhost/ballroom/provider/buscar","name":" Buscar Fornecedor(es)","description":"","method":"POST","body":{"mimeType":"application/x-www-form-urlencoded","params":[]},"parameters":[],"headers":[{"id":"pair_a459fc0119df40159d3c27fc59e2f91d","name":"","value":"","description":""},{"name":"Content-Type","value":"application/x-www-form-urlencoded","id":"pair_6af7f290a4d04a1aad439af3e7af99b6"}],"authentication":{},"metaSortKey":-1645396281601.5,"isPrivate":false,"settingStoreCookies":true,"settingSendCookies":true,"settingDisableRenderRequestBody":false,"settingEncodeUrl":true,"settingRebuildPath":true,"settingFollowRedirects":"global","_type":"request"},{"_id":"req_b247ec1cbdee49d1a507365ad1f0562a","parentId":"fld_bf988367be0f4889be7cfdcf2d76706d","modified":1646404222039,"created":1646355737619,"url":"http://localhost/ballroom/index.php/provider/cadastrar","name":"Criar Login Fornecedor","description":"","method":"POST","body":{"mimeType":"application/x-www-form-urlencoded","params":[{"id":"pair_0be9ee56a3b6409c838b2968fe3cc019","name":"email","value":"wagner12107@gmail.com","description":""},{"id":"pair_5ad8fa61065e4a3c9ceb014f0cb24e71","name":"password","value":"123456","description":""}]},"parameters":[],"headers":[{"id":"pair_a459fc0119df40159d3c27fc59e2f91d","name":"","value":"","description":""},{"name":"Content-Type","value":"application/x-www-form-urlencoded","id":"pair_6af7f290a4d04a1aad439af3e7af99b6"}],"authentication":{},"metaSortKey":-1645396281551.5,"isPrivate":false,"settingStoreCookies":true,"settingSendCookies":true,"settingDisableRenderRequestBody":false,"settingEncodeUrl":true,"settingRebuildPath":true,"settingFollowRedirects":"global","_type":"request"},{"_id":"req_15fdfedc40c549bd8810b18506b43616","parentId":"fld_bf988367be0f4889be7cfdcf2d76706d","modified":1646368215177,"created":1646359032396,"url":"http://localhost/ballroom/index.php/provider/deletar","name":"Apagar Login Fornecedor","description":"","method":"POST","body":{"mimeType":"application/x-www-form-urlencoded","params":[{"name":"email","value":"wagner1107@gmail.com","id":"pair_8715192ec2ad47669eef6e0d8ff95709"}]},"parameters":[],"headers":[{"id":"pair_a459fc0119df40159d3c27fc59e2f91d","name":"","value":"","description":""},{"name":"Content-Type","value":"application/x-www-form-urlencoded","id":"pair_6af7f290a4d04a1aad439af3e7af99b6"}],"authentication":{},"metaSortKey":-1645396281526.5,"isPrivate":false,"settingStoreCookies":true,"settingSendCookies":true,"settingDisableRenderRequestBody":false,"settingEncodeUrl":true,"settingRebuildPath":true,"settingFollowRedirects":"global","_type":"request"},{"_id":"req_6d149bbff8934865861e37764560864c","parentId":"fld_bf988367be0f4889be7cfdcf2d76706d","modified":1646404525867,"created":1646360841669,"url":"http://localhost/ballroom/index.php/provider/cadastrarDados","name":"Cadastrar/Atualizar Mais Informações","description":"","method":"POST","body":{"mimeType":"application/x-www-form-urlencoded","params":[{"id":"pair_2d18cdc6c8174fb6acab3baa818d00a9","name":"name","value":"Wagner Augusto Mendes dos Santos","description":""},{"id":"pair_fd1c5608a0ca48bca3105ad4ae7fdbcf","name":"description","value":"Desenvolvedor de Software","description":""},{"id":"pair_25d236ea286e401f93dc8284b5cf04fc","name":"document","value":"41819644855","description":""},{"id":"pair_69204c15ffad4b9ebd11ddb0c348d594","name":"email","value":"wagner1107@hotmail.com","description":""}]},"parameters":[],"headers":[{"id":"pair_a459fc0119df40159d3c27fc59e2f91d","name":"","value":"","description":""},{"name":"Content-Type","value":"application/x-www-form-urlencoded","id":"pair_6af7f290a4d04a1aad439af3e7af99b6"}],"authentication":{},"metaSortKey":-1645396281464,"isPrivate":false,"settingStoreCookies":true,"settingSendCookies":true,"settingDisableRenderRequestBody":false,"settingEncodeUrl":true,"settingRebuildPath":true,"settingFollowRedirects":"global","_type":"request"},{"_id":"req_a6464cb5621c481a8c643f5c9300a620","parentId":"fld_bf988367be0f4889be7cfdcf2d76706d","modified":1646369373656,"created":1646365209504,"url":"http://localhost/ballroom/index.php/provider/deletarDados","name":"Apagar Mais Informações","description":"","method":"POST","body":{"mimeType":"application/x-www-form-urlencoded","params":[{"id":"pair_25d236ea286e401f93dc8284b5cf04fc","name":"documento","value":"41819644855","description":""}]},"parameters":[],"headers":[{"id":"pair_a459fc0119df40159d3c27fc59e2f91d","name":"","value":"","description":""},{"name":"Content-Type","value":"application/x-www-form-urlencoded","id":"pair_6af7f290a4d04a1aad439af3e7af99b6"}],"authentication":{},"metaSortKey":-1644916553374,"isPrivate":false,"settingStoreCookies":true,"settingSendCookies":true,"settingDisableRenderRequestBody":false,"settingEncodeUrl":true,"settingRebuildPath":true,"settingFollowRedirects":"global","_type":"request"},{"_id":"req_a0826b48728642f380af92f96e54b51b","parentId":"fld_bf988367be0f4889be7cfdcf2d76706d","modified":1646404512580,"created":1646366714234,"url":"http://localhost/ballroom/index.php/provider/cadastrarDadosBancarios","name":"Cadastrar Dados Bancários","description":"","method":"POST","body":{"mimeType":"application/x-www-form-urlencoded","params":[{"id":"pair_9b10f422adda41ef984e396ef1d737d4","name":"banco","value":"Itau","description":""},{"id":"pair_dbb27ed4d0cf4fd09c8413dac6b482bd","name":"agencia","value":"1234","description":""},{"id":"pair_f9b95fa828cd413f845b7f66ed73affc","name":"conta","value":"43212","description":""},{"id":"pair_b867eee6b4f74ebf80ac4d606514a048","name":"digito","value":"100","description":""},{"id":"pair_f25054ff34d74e8a85d46cde909ae45b","name":"tipo","value":"corrente","description":""},{"id":"pair_358253dd04294399b18bc36c7ca8cb8b","name":"email","value":"wagner1107@Hotmail.com","description":""}]},"parameters":[],"headers":[{"id":"pair_a459fc0119df40159d3c27fc59e2f91d","name":"","value":"","description":""},{"name":"Content-Type","value":"application/x-www-form-urlencoded","id":"pair_6af7f290a4d04a1aad439af3e7af99b6"}],"authentication":{},"metaSortKey":-1644676689329,"isPrivate":false,"settingStoreCookies":true,"settingSendCookies":true,"settingDisableRenderRequestBody":false,"settingEncodeUrl":true,"settingRebuildPath":true,"settingFollowRedirects":"global","_type":"request"},{"_id":"req_458dd307454d4324a356aac0c4529a16","parentId":"fld_bf988367be0f4889be7cfdcf2d76706d","modified":1646369607442,"created":1646367772384,"url":"http://localhost/ballroom/index.php/provider/deletarDadosBancarios","name":"Apagar Dados Bancarios","description":"","method":"POST","body":{"mimeType":"application/x-www-form-urlencoded","params":[{"id":"pair_25d236ea286e401f93dc8284b5cf04fc","name":"conta","value":"4321","description":""}]},"parameters":[],"headers":[{"id":"pair_a459fc0119df40159d3c27fc59e2f91d","name":"","value":"","description":""},{"name":"Content-Type","value":"application/x-www-form-urlencoded","id":"pair_6af7f290a4d04a1aad439af3e7af99b6"}],"authentication":{},"metaSortKey":-1644676689279,"isPrivate":false,"settingStoreCookies":true,"settingSendCookies":true,"settingDisableRenderRequestBody":false,"settingEncodeUrl":true,"settingRebuildPath":true,"settingFollowRedirects":"global","_type":"request"},{"_id":"env_47f7c68c869f0071dc3c3c2dfb5f401318bc72cb","parentId":"wrk_cf0f3856a17c4040b96c56899e3e63b0","modified":1646405318408,"created":1643397915294,"name":"Base Environment","data":{},"dataPropertyOrder":{},"color":null,"isPrivate":false,"metaSortKey":1643397915294,"_type":"environment"},{"_id":"jar_47f7c68c869f0071dc3c3c2dfb5f401318bc72cb","parentId":"wrk_cf0f3856a17c4040b96c56899e3e63b0","modified":1646405234423,"created":1643397915295,"name":"Default Jar","cookies":[{"key":"ci_session","value":"sg98onhe29nag51phb57fiego36d7vtj","expires":"2022-03-04T16:47:13.000Z","maxAge":7200,"domain":"localhost","path":"/","httpOnly":true,"hostOnly":true,"creation":"2022-03-04T14:47:14.422Z","lastAccessed":"2022-03-04T14:47:14.422Z","id":"25670828369210064"}],"_type":"cookie_jar"},{"_id":"spc_f4824cee4ef34900ac56e0c8456393f0","parentId":"wrk_cf0f3856a17c4040b96c56899e3e63b0","modified":1643397915288,"created":1643397915288,"fileName":"AssinaDigi","contents":"","contentType":"yaml","_type":"api_spec"},{"_id":"env_8b232f7f51cf44bc855500da2cab8886","parentId":"env_47f7c68c869f0071dc3c3c2dfb5f401318bc72cb","modified":1646405324185,"created":1646405320471,"name":"Ballroom","data":{},"dataPropertyOrder":{},"color":null,"isPrivate":false,"metaSortKey":1646405320471,"_type":"environment"}]}